xpw/__init__.py
xpw/account.py
xpw/attribute.py
xpw/authorize.py
xpw/configure.py
xpw/ldapauth.py
xpw/password.py
xpw/pwhasher.py
xpw/randkey.py
xpw/session.py
xpw-0.15.1.dist-info/LICENSE
xpw-0.15.1.dist-info/METADATA
xpw-0.15.1.dist-info/WHEEL
xpw-0.15.1.dist-info/entry_points.txt
xpw-0.15.1.dist-info/top_level.txt
xpw-0.15.1.dist-info/zip-safe
xpw-0.15.1.dist-info/RECORD
