Metadata-Version: 2.1
Name: xpw
Version: 0.15.1
Summary: Password management and authentication
Home-page: https://github.com/bondbox/xpw/
Author: Mingzhe Zou
Author-email: zoumingzhe@outlook.com
License: GPLv2
Project-URL: Source Code, https://github.com/bondbox/xpw/
Project-URL: Bug Tracker, https://github.com/bondbox/xpw/issues
Project-URL: Documentation, https://github.com/bondbox/xpw/
Keywords: command-line,argparse,argcomplete
Platform: any
Classifier: Programming Language :: Python
Classifier: Programming Language :: Python :: 3
Requires-Python: >=3.8
License-File: LICENSE
Requires-Dist: xkits-command >=0.5
Requires-Dist: xkits-file >=0.6
Requires-Dist: xkits-lib >=0.4
Requires-Dist: argon2-cffi
Requires-Dist: ldap3
Requires-Dist: toml
